hckmtrx_tools/__init__.py
hckmtrx_tools/hckmtrx_tools.py
hckmtrx_tools-0.0.6.dist-info/LICENSE
hckmtrx_tools-0.0.6.dist-info/METADATA
hckmtrx_tools-0.0.6.dist-info/WHEEL
hckmtrx_tools-0.0.6.dist-info/top_level.txt
hckmtrx_tools-0.0.6.dist-info/RECORD
