Metadata-Version: 2.1
Name: hckmtrx-tools
Version: 0.0.6
Summary: tools for improved coding
Author: hckmtrx
Author-email: <hckmtrx@gmail.com>
Keywords: python,tools
Classifier: Development Status :: 1 - Planning
Classifier: Intended Audience :: Developers
Classifier: Programming Language :: Python :: 3
Classifier: Operating System :: Unix
Classifier: Operating System :: MacOS :: MacOS X
Classifier: Operating System :: Microsoft :: Windows
License-File: LICENSE
